{
    "2": {
        "chunk_key": "chunk-f0754e4a10d4afb3328d0c2f3aa4c1d6",
        "entities": [
            {
                "entity_name": "\"HARRIET HAGEMAN\"",
                "entity_type": "\"PERSON\"",
                "description": "\"Harriet Hageman is a political figure who received the most votes in a primary election, as mentioned by Ms. Cheney.\"",
                "source_id": "chunk-f0754e4a10d4afb3328d0c2f3aa4c1d6"
            },
            {
                "entity_name": "\"MS. CHENEY\"",
                "entity_type": "\"PERSON\"",
                "description": "\"Ms. Cheney is a supporter who announced Harriet Hageman's victory in a primary election and called for Americans to stand up to Mr. Trump and others who deny his loss in the 2020 presidential election.\"",
                "source_id": "chunk-f0754e4a10d4afb3328d0c2f3aa4c1d6"
            },
            {
                "entity_name": "\"MR. TRUMP\"",
                "entity_type": "\"PERSON\"",
                "description": "\"Mr. Trump is mentioned as someone who, along with others, denies his loss in the 2020 presidential election, according to Ms. Cheney.\"",
                "source_id": "chunk-f0754e4a10d4afb3328d0c2f3aa4c1d6"
            },
            {
                "entity_name": "\"2020 PRESIDENTIAL ELECTION\"",
                "entity_type": "\"EVENT\"",
                "description": "The 2020 Presidential Election is an event where Mr. Trump is claimed to have lost, and it is a point of contention for those who deny his loss.",
                "source_id": "chunk-f0754e4a10d4afb3328d0c2f3aa4c1d6"
            },
            {
                "entity_name": "\"ANDREW M. CUOMO\"",
                "entity_type": "\"PERSON\"",
                "description": "\"Andrew M. Cuomo is a former governor who won an ethics lawsuit, allowing him to keep the proceeds from his book deal about the pandemic.\"",
                "source_id": "chunk-f0754e4a10d4afb3328d0c2f3aa4c1d6"
            },
            {
                "entity_name": "\"UKRAINE\"",
                "entity_type": "\"GEO\"",
                "description": "\"Ukraine is a country whose government is working to save businesses from Russian bombs by moving factories west, creating a new industrial and economic heartland.\"",
                "source_id": "chunk-f0754e4a10d4afb3328d0c2f3aa4c1d6"
            },
            {
                "entity_name": "\"RUSSIA\"",
                "entity_type": "\"GEO\"",
                "description": "\"Russia is a country that earns billions of dollars from the production of diamonds, which other nations claim help finance war, and is also bombing businesses in eastern Ukraine.\"",
                "source_id": "chunk-f0754e4a10d4afb3328d0c2f3aa4c1d6"
            },
            {
                "entity_name": "\"KENYA\"",
                "entity_type": "\"GEO\"",
                "description": "\"Kenya is a country where Raila Odinga, who lost the presidential election, plans to use all legal options to fight the result.\"",
                "source_id": "chunk-f0754e4a10d4afb3328d0c2f3aa4c1d6"
            },
            {
                "entity_name": "\"JESUITS\"",
                "entity_type": "\"ORGANIZATION\"",
                "description": "\"The Jesuits are an order that set a goal to raise $100 million to make amends for their role in the slave trade, but donations have been slow.\"",
                "source_id": "chunk-f0754e4a10d4afb3328d0c2f3aa4c1d6"
            },
            {
                "entity_name": "\"SABRINA IONESCU\"",
                "entity_type": "\"PERSON\"",
                "description": "\"Sabrina Ionescu is a player relied upon by the Liberty in the W.N.B.A. playoffs, having a breakout season in her third year.\"",
                "source_id": "chunk-f0754e4a10d4afb3328d0c2f3aa4c1d6"
            },
            {
                "entity_name": "\"RUSSIAN GEMS\"",
                "entity_type": "\"EVENT\"",
                "description": "\"The production of Russian gems, particularly diamonds, is an event that earns Russia billions of dollars and is claimed to finance war by other nations.\"",
                "source_id": "chunk-f0754e4a10d4afb3328d0c2f3aa4c1d6"
            },
            {
                "entity_name": "\"KENYA VOTE\"",
                "entity_type": "\"EVENT\"",
                "description": "\"The Kenya Vote refers to the nation's presidential election, the result of which Raila Odinga, the loser, plans to legally challenge.\"",
                "source_id": "chunk-f0754e4a10d4afb3328d0c2f3aa4c1d6"
            },
            {
                "entity_name": "\"JESUITS' ATONEMENT FUND\"",
                "entity_type": "\"EVENT\"",
                "description": "\"The Jesuits' Atonement Fund is an event where the Jesuits aim to raise $100 million to atone for their role in the slave trade, but have seen slow donations.\"",
                "source_id": "chunk-f0754e4a10d4afb3328d0c2f3aa4c1d6"
            },
            {
                "entity_name": "\"ART OR A COPYRIGHT ISSUE\"",
                "entity_type": "\"EVENT\"",
                "description": "\"The Supreme Court's decision on whether Andy Warhol's interpretation of a photograph of Prince is protected as a transformative work is an event that addresses the intersection of art and copyright.\"",
                "source_id": "chunk-f0754e4a10d4afb3328d0c2f3aa4c1d6"
            },
            {
                "entity_name": "\"TAQUIZA\"",
                "entity_type": "\"EVENT\"",
                "description": "\"Taquiza is an event suggested for an end-of-summer party where guests can make their own tacos from a spread of ingredients.\"",
                "source_id": "chunk-f0754e4a10d4afb3328d0c2f3aa4c1d6"
            },
            {
                "entity_name": "\"SALVAGE STORES\"",
                "entity_type": "\"EVENT\"",
                "description": "\"Salvage Stores Catch On refers to the event where frugal shoppers find bargains in dented cans, ignored sell-by dates, and new-product flops.\"",
                "source_id": "chunk-f0754e4a10d4afb3328d0c2f3aa4c1d6"
            },
            {
                "entity_name": "\"‘SAUL’ TIME MACHINE\"",
                "entity_type": "\"EVENT\"",
                "description": "\"The ‘Saul’ Time Machine is an event that describes the TV show 'Better Call Saul' and its finale, which seamlessly looked back at the character's past and forward to his future.\"",
                "source_id": "chunk-f0754e4a10d4afb3328d0c2f3aa4c1d6"
            },
            {
                "entity_name": "\"W.N.B.A. PLAYOFFS\"",
                "entity_type": "\"EVENT\"",
                "description": "\"The W.N.B.A. playoffs is an event where the Liberty team is relying on Sabrina Ionescu for a strong performance in her third year.\"",
                "source_id": "chunk-f0754e4a10d4afb3328d0c2f3aa4c1d6"
            }
        ],
        "relationships": [
            {
                "src_id": "\"HARRIET HAGEMAN\"",
                "tgt_id": "\"MS. CHENEY\"",
                "weight": 8.0,
                "description": "\"Ms. Cheney announced Harriet Hageman's victory in the primary election.\"",
                "source_id": "chunk-f0754e4a10d4afb3328d0c2f3aa4c1d6"
            },
            {
                "src_id": "\"MS. CHENEY\"",
                "tgt_id": "\"MR. TRUMP\"",
                "weight": 7.0,
                "description": "\"Ms. Cheney called for Americans to stand up to Mr. Trump and others who deny his loss in the 2020 presidential election.\"",
                "source_id": "chunk-f0754e4a10d4afb3328d0c2f3aa4c1d6"
            },
            {
                "src_id": "\"UKRAINE\"",
                "tgt_id": "\"RUSSIA\"",
                "weight": 9.0,
                "description": "\"Ukraine's government is working to save businesses from Russian bombs, indicating a conflict between the two nations.\"",
                "source_id": "chunk-f0754e4a10d4afb3328d0c2f3aa4c1d6"
            },
            {
                "src_id": "\"RUSSIA\"",
                "tgt_id": "\"RUSSIAN GEMS\"",
                "weight": 9.0,
                "description": "\"Russia earns billions of dollars from the production of diamonds, which is the subject of the Russian Gems event.\"",
                "source_id": "chunk-f0754e4a10d4afb3328d0c2f3aa4c1d6"
            },
            {
                "src_id": "\"JESUITS\"",
                "tgt_id": "\"JESUITS' ATONEMENT FUND\"",
                "weight": 7.0,
                "description": "\"The Jesuits initiated the Jesuits' Atonement Fund to raise money for their role in the slave trade.\"",
                "source_id": "chunk-f0754e4a10d4afb3328d0c2f3aa4c1d6"
            },
            {
                "src_id": "\"SABRINA IONESCU\"",
                "tgt_id": "\"W.N.B.A. PLAYOFFS\"",
                "weight": 7.0,
                "description": "\"Sabrina Ionescu is relied upon by the Liberty in the W.N.B.A. playoffs, indicating her importance to the team's performance in the event.\"",
                "source_id": "chunk-f0754e4a10d4afb3328d0c2f3aa4c1d6"
            }
        ]
    },
    "0": {
        "chunk_key": "chunk-67fe1d2659877b616b671685d43d7605",
        "entities": [
            {
                "entity_name": "\"THE NEW YORK TIMES COMPANY\"",
                "entity_type": "\"ORGANIZATION\"",
                "description": "\"The New York Times Company is the publisher of the newspaper, providing news and information to its readers.\"",
                "source_id": "chunk-67fe1d2659877b616b671685d43d7605"
            },
            {
                "entity_name": "\"HENRY FOUNTAIN\"",
                "entity_type": "\"PERSON\"",
                "description": "\"Henry Fountain is the author of the article discussing water restrictions in the Colorado River and its impact on Arizona and Nevada.\"",
                "source_id": "chunk-67fe1d2659877b616b671685d43d7605"
            },
            {
                "entity_name": "\"COLORADO RIVER\"",
                "entity_type": "\"GEO\"",
                "description": "\"The Colorado River is a significant water source in the Southwest, currently facing a crisis due to low water levels and drought.\"",
                "source_id": "chunk-67fe1d2659877b616b671685d43d7605"
            },
            {
                "entity_name": "\"LAKE POWELL\"",
                "entity_type": "\"GEO\"",
                "description": "\"Lake Powell is a reservoir on the Colorado River, located on the Arizona-Utah border, with water levels at 28 percent of total capacity.\"",
                "source_id": "chunk-67fe1d2659877b616b671685d43d7605"
            },
            {
                "entity_name": "\"LAKE MEAD\"",
                "entity_type": "\"GEO\"",
                "description": "\"Lake Mead is another reservoir on the Colorado River, with water levels at 28 percent of total capacity due to diminished flow and increased demand.\"",
                "source_id": "chunk-67fe1d2659877b616b671685d43d7605"
            },
            {
                "entity_name": "\"ARIZONA\"",
                "entity_type": "\"GEO\"",
                "description": "\"Arizona is a state facing new restrictions on the amount of water that can be pumped out of the Colorado River due to the water crisis.\"",
                "source_id": "chunk-67fe1d2659877b616b671685d43d7605"
            },
            {
                "entity_name": "\"NEVADA\"",
                "entity_type": "\"GEO\"",
                "description": "\"Nevada is a state facing new restrictions on the amount of water that can be pumped out of the Colorado River due to the water crisis.\"",
                "source_id": "chunk-67fe1d2659877b616b671685d43d7605"
            },
            {
                "entity_name": "\"MEXICO\"",
                "entity_type": "\"GEO\"",
                "description": "\"Mexico is affected by the new water cuts imposed on the Colorado River, which supplies water to 40 million people in the United States and Mexico.\"",
                "source_id": "chunk-67fe1d2659877b616b671685d43d7605"
            },
            {
                "entity_name": "\"MICHAEL SCHWIRTZ\"",
                "entity_type": "\"PERSON\"",
                "description": "\"Michael Schwirtz is the author of the article discussing Ukraine's military tactics against Crimea.\"",
                "source_id": "chunk-67fe1d2659877b616b671685d43d7605"
            },
            {
                "entity_name": "\"ANTON TROIANOVSKI\"",
                "entity_type": "\"PERSON\"",
                "description": "\"Anton Troianovski is the co-author of the article discussing Ukraine's military tactics against Crimea.\"",
                "source_id": "chunk-67fe1d2659877b616b671685d43d7605"
            },
            {
                "entity_name": "\"UKRAINE\"",
                "entity_type": "\"GEO\"",
                "description": "\"Ukraine is a country that has been conducting clandestine assaults against Crimea, which is under Russian occupation.\"",
                "source_id": "chunk-67fe1d2659877b616b671685d43d7605"
            },
            {
                "entity_name": "\"CRIMEA\"",
                "entity_type": "\"GEO\"",
                "description": "\"Crimea is a peninsula that has been illegally annexed by Russia in 2014 and is now a vital staging ground for Russia's invasion.\"",
                "source_id": "chunk-67fe1d2659877b616b671685d43d7605"
            },
            {
                "entity_name": "\"VLADIMIR V. PUTIN\"",
                "entity_type": "\"PERSON\"",
                "description": "\"Vladimir V. Putin is the President of Russia, who has called Crimea a 'sacred place' and warned of severe consequences if it is attacked.\"",
                "source_id": "chunk-67fe1d2659877b616b671685d43d7605"
            },
            {
                "entity_name": "\"CHRISTINA JEWETT\"",
                "entity_type": "\"PERSON\"",
                "description": "\"Christina Jewett is the author of the article discussing the FDA's decision to allow over-the-counter sales of hearing aids.\"",
                "source_id": "chunk-67fe1d2659877b616b671685d43d7605"
            },
            {
                "entity_name": "\"FOOD AND DRUG ADMINISTRATION\"",
                "entity_type": "\"ORGANIZATION\"",
                "description": "\"The Food and Drug Administration is a government agency that has decided to allow hearing aids to be sold over the counter without a prescription to adults.\"",
                "source_id": "chunk-67fe1d2659877b616b671685d43d7605"
            },
            {
                "entity_name": "\"RUSSIAN WARSHIPS\"",
                "entity_type": "\"ORGANIZATION\"",
                "description": "\"Russian warships patrol Crimea's coasts, indicating Russia's military presence and control over the area.\"",
                "source_id": "chunk-67fe1d2659877b616b671685d43d7605"
            },
            {
                "entity_name": "\"RUSSIAN WARPLANES\"",
                "entity_type": "\"ORGANIZATION\"",
                "description": "\"Russian warplanes operate from Crimea, highlighting the region's use as a base for Russian military operations.\"",
                "source_id": "chunk-67fe1d2659877b616b671685d43d7605"
            },
            {
                "entity_name": "\"KYIV\"",
                "entity_type": "\"GEO\"",
                "description": "\"Kyiv is the capital of Ukraine, where the government is leveraging Western weapons and special forces to conduct military operations.\"",
                "source_id": "chunk-67fe1d2659877b616b671685d43d7605"
            },
            {
                "entity_name": "\"ELITE UKRAINIAN MILITARY UNIT\"",
                "entity_type": "\"ORGANIZATION\"",
                "description": "\"The elite Ukrainian military unit is responsible for the blasts in Crimea, operating behind enemy lines and challenging Russian occupation.\"",
                "source_id": "chunk-67fe1d2659877b616b671685d43d7605"
            },
            {
                "entity_name": "\"RUSSIA'S DEFENSE MINISTRY\"",
                "entity_type": "\"ORGANIZATION\"",
                "description": "\"Russia's Defense Ministry acknowledged the Crimea explosions as an 'act of sabotage,' indicating the spread of the war to Russian territory.\"",
                "source_id": "chunk-67fe1d2659877b616b671685d43d7605"
            },
            {
                "entity_name": "\"JUDGMENT DAY\"",
                "entity_type": "\"CONCEPT\"",
                "description": "\"'Judgment Day' is a term used by a Russian top adviser to describe the severe consequences Ukraine would face if Crimea were attacked.\"",
                "source_id": "chunk-67fe1d2659877b616b671685d43d7605"
            },
            {
                "entity_name": "\"BLACK SEA PENINSULA\"",
                "entity_type": "\"GEO\"",
                "description": "\"The Black Sea peninsula refers to Crimea, which is the target of Ukrainian assaults and a vital staging ground for Russia's invasion.\"",
                "source_id": "chunk-67fe1d2659877b616b671685d43d7605"
            },
            {
                "entity_name": "\"PUTIN'S ANNEXATION OF CRIMEA\"",
                "entity_type": "\"EVENT\"",
                "description": "\"Putin's annexation of Crimea is the event where Russia took control of the peninsula in 2014, which has significant political implications for Putin's image and Russia's military efforts.\"",
                "source_id": "chunk-67fe1d2659877b616b671685d43d7605"
            }
        ],
        "relationships": [
            {
                "src_id": "\"THE NEW YORK TIMES COMPANY\"",
                "tgt_id": "\"HENRY FOUNTAIN\"",
                "weight": 6.0,
                "description": "\"Henry Fountain is a writer for The New York Times Company, contributing articles on various topics.\"",
                "source_id": "chunk-67fe1d2659877b616b671685d43d7605"
            },
            {
                "src_id": "\"ARIZONA\"",
                "tgt_id": "\"COLORADO RIVER\"",
                "weight": 8.0,
                "description": "\"Arizona is a state that relies on the Colorado River for water, and is now facing restrictions on water pumping.\"",
                "source_id": "chunk-67fe1d2659877b616b671685d43d7605"
            },
            {
                "src_id": "\"NEVADA\"",
                "tgt_id": "\"COLORADO RIVER\"",
                "weight": 8.0,
                "description": "\"Nevada is a state that relies on the Colorado River for water, and is now facing restrictions on water pumping.\"",
                "source_id": "chunk-67fe1d2659877b616b671685d43d7605"
            },
            {
                "src_id": "\"LAKE POWELL\"",
                "tgt_id": "\"COLORADO RIVER\"",
                "weight": 7.0,
                "description": "\"Lake Powell is a reservoir on the Colorado River, significantly affected by the water crisis.\"",
                "source_id": "chunk-67fe1d2659877b616b671685d43d7605"
            },
            {
                "src_id": "\"LAKE MEAD\"",
                "tgt_id": "\"COLORADO RIVER\"",
                "weight": 7.0,
                "description": "\"Lake Mead is a reservoir on the Colorado River, significantly affected by the water crisis.\"",
                "source_id": "chunk-67fe1d2659877b616b671685d43d7605"
            },
            {
                "src_id": "\"PUTIN'S ANNEXATION OF CRIMEA\"",
                "tgt_id": "\"VLADIMIR V. PUTIN\"",
                "weight": 10.0,
                "description": "\"Vladimir V. Putin is the Russian President who annexed Crimea in 2014, significantly impacting his political standing and Russia's military efforts.\"",
                "source_id": "chunk-67fe1d2659877b616b671685d43d7605"
            },
            {
                "src_id": "\"PUTIN'S ANNEXATION OF CRIMEA\"",
                "tgt_id": "\"CRIMEA\"",
                "weight": 10.0,
                "description": "\"The annexation of Crimea by Putin transformed the peninsula into a fortress and a vital staging ground for Russia's invasion.\"",
                "source_id": "chunk-67fe1d2659877b616b671685d43d7605"
            }
        ]
    },
    "1": {
        "chunk_key": "chunk-1ffb4e2302caebd3fef76d6d2ad04cec",
        "entities": [
            {
                "entity_name": "\"JOE BIDEN\"",
                "entity_type": "\"PERSON\"",
                "description": "\"Joe Biden is the President of the United States who signed a significant tax, health, and energy bill aimed at modernizing the American economy and reducing dependence on fossil fuels.\"",
                "source_id": "chunk-1ffb4e2302caebd3fef76d6d2ad04cec"
            },
            {
                "entity_name": "\"INFLATION REDUCTION ACT\"",
                "entity_type": "\"EVENT\"",
                "description": "\"The Inflation Reduction Act is a landmark legislation signed by President Biden, which includes provisions to lower prescription drug costs, extend health insurance subsidies, and reduce the federal deficit, among other things.\"",
                "source_id": "chunk-1ffb4e2302caebd3fef76d6d2ad04cec"
            },
            {
                "entity_name": "\"MEDICARE\"",
                "entity_type": "\"ORGANIZATION\"",
                "description": "\"Medicare is a federal program that provides health insurance for seniors, and the Inflation Reduction Act includes provisions to lower prescription drug costs for seniors on Medicare.\"",
                "source_id": "chunk-1ffb4e2302caebd3fef76d6d2ad04cec"
            },
            {
                "entity_name": "\"AMERICAN ECONOMY\"",
                "entity_type": "\"GEO\"",
                "description": "\"The American economy is the focus of President Biden's goal to modernize it and reduce its dependence on fossil fuels through the Inflation Reduction Act.\"",
                "source_id": "chunk-1ffb4e2302caebd3fef76d6d2ad04cec"
            },
            {
                "entity_name": "\"WASHINGTON\"",
                "entity_type": "\"GEO\"",
                "description": "\"Washington is the location where President Biden signed the Inflation Reduction Act into law.\"",
                "source_id": "chunk-1ffb4e2302caebd3fef76d6d2ad04cec"
            },
            {
                "entity_name": "\"DONALD J. TRUMP\"",
                "entity_type": "\"PERSON\"",
                "description": "\"Donald J. Trump is the former President of the United States who approved a \\$3.1 trillion relief package in 2020, and his actions and influence are mentioned in the context of the fraud during the pandemic and the Republican Party.\"",
                "source_id": "chunk-1ffb4e2302caebd3fef76d6d2ad04cec"
            },
            {
                "entity_name": "\"RICHARD AYVAZYAN\"",
                "entity_type": "\"PERSON\"",
                "description": "\"Richard Ayvazyan is part of a ring that sought billions in loans and received 17 years in prison, mentioned in the context of pandemic-related fraud.\"",
                "source_id": "chunk-1ffb4e2302caebd3fef76d6d2ad04cec"
            },
            {
                "entity_name": "\"LIZ CHENEY\"",
                "entity_type": "\"PERSON\"",
                "description": "\"Liz Cheney is a Representative from Wyoming and a vocal critic of Donald J. Trump, who lost her Republican primary to Harriet Hageman.\"",
                "source_id": "chunk-1ffb4e2302caebd3fef76d6d2ad04cec"
            },
            {
                "entity_name": "\"HARRIET HAGEMAN\"",
                "entity_type": "\"PERSON\"",
                "description": "\"Harriet Hageman is a lawyer in Cheyenne who was endorsed by Donald J. Trump and won the Republican primary against Liz Cheney.\"",
                "source_id": "chunk-1ffb4e2302caebd3fef76d6d2ad04cec"
            },
            {
                "entity_name": "\"COSTCO\"",
                "entity_type": "\"ORGANIZATION\"",
                "description": "\"Costco is a retailer where hearing aids are available at a lower cost compared to other providers, starting at about \\$1,400.\"",
                "source_id": "chunk-1ffb4e2302caebd3fef76d6d2ad04cec"
            },
            {
                "entity_name": "\"ELECTRIC UTILITIES\"",
                "entity_type": "\"ORGANIZATION\"",
                "description": "\"Electric utilities are entities that will be helped by the legislation to switch to lower-emission sources of energy.\"",
                "source_id": "chunk-1ffb4e2302caebd3fef76d6d2ad04cec"
            },
            {
                "entity_name": "\"AMERICANS\"",
                "entity_type": "\"PERSON\"",
                "description": "\"Americans are the general population who will be encouraged to buy electric vehicles through tax credits provided by the legislation.\"",
                "source_id": "chunk-1ffb4e2302caebd3fef76d6d2ad04cec"
            },
            {
                "entity_name": "\"CONGRESSIONAL DEMOCRATS\"",
                "entity_type": "\"ORGANIZATION\"",
                "description": "\"Congressional Democrats are the group of politicians who engaged in intense negotiations for over a year to pass the Inflation Reduction Act.\"",
                "source_id": "chunk-1ffb4e2302caebd3fef76d6d2ad04cec"
            },
            {
                "entity_name": "\"DEMOCRATIC PARTY\"",
                "entity_type": "\"ORGANIZATION\"",
                "description": "\"The Democratic Party is the political party to which President Biden belongs and which has a razor-thin majority in the House and Senate.\"",
                "source_id": "chunk-1ffb4e2302caebd3fef76d6d2ad04cec"
            },
            {
                "entity_name": "\"HOUSE OF REPRESENTATIVES\"",
                "entity_type": "\"ORGANIZATION\"",
                "description": "\"The House of Representatives is one of the two chambers of the United States Congress where the Democratic Party has a slim majority.\"",
                "source_id": "chunk-1ffb4e2302caebd3fef76d6d2ad04cec"
            },
            {
                "entity_name": "\"SENATE\"",
                "entity_type": "\"ORGANIZATION\"",
                "description": "\"The Senate is the upper chamber of the United States Congress where the Democratic Party holds a narrow majority.\"",
                "source_id": "chunk-1ffb4e2302caebd3fef76d6d2ad04cec"
            },
            {
                "entity_name": "\"F.B.I.\"",
                "entity_type": "\"ORGANIZATION\"",
                "description": "\"The F.B.I. is involved in investigating pandemic-fraud cases along with other federal agencies.\"",
                "source_id": "chunk-1ffb4e2302caebd3fef76d6d2ad04cec"
            },
            {
                "entity_name": "\"SECRET SERVICE\"",
                "entity_type": "\"ORGANIZATION\"",
                "description": "\"The Secret Service is one of the federal agencies working on pandemic-fraud cases.\"",
                "source_id": "chunk-1ffb4e2302caebd3fef76d6d2ad04cec"
            },
            {
                "entity_name": "\"POSTAL INSPECTION SERVICE\"",
                "entity_type": "\"ORGANIZATION\"",
                "description": "\"The Postal Inspection Service is involved in the investigation of fraud related to the pandemic.\"",
                "source_id": "chunk-1ffb4e2302caebd3fef76d6d2ad04cec"
            },
            {
                "entity_name": "\"INTERNAL REVENUE SERVICE\"",
                "entity_type": "\"ORGANIZATION\"",
                "description": "\"The Internal Revenue Service is a federal agency that has charged people with defrauding pandemic-aid programs.\"",
                "source_id": "chunk-1ffb4e2302caebd3fef76d6d2ad04cec"
            },
            {
                "entity_name": "\"DO NOT PAY LIST\"",
                "entity_type": "\"CONCEPT\"",
                "description": "\"The 'Do Not Pay List' is a government list that includes people who should not receive payments, yet some of them received relief money during the pandemic.\"",
                "source_id": "chunk-1ffb4e2302caebd3fef76d6d2ad04cec"
            },
            {
                "entity_name": "\"N/A\"",
                "entity_type": "\"CONCEPT\"",
                "description": "\"'N/A' refers to the non-applicable or not available designation used by 342 people who received loans during the pandemic, indicating potential fraud.\"",
                "source_id": "chunk-1ffb4e2302caebd3fef76d6d2ad04cec"
            },
            {
                "entity_name": "\"JAN. 6 CAPITOL ATTACK\"",
                "entity_type": "\"EVENT\"",
                "description": "\"The Jan. 6 Capitol Attack is an event that Liz Cheney, as vice chairwoman of the committee investigating it, is vocally against and which is central to her political stance against Donald J. Trump.\"",
                "source_id": "chunk-1ffb4e2302caebd3fef76d6d2ad04cec"
            },
            {
                "entity_name": "\"REPUBLICAN PARTY\"",
                "entity_type": "\"ORGANIZATION\"",
                "description": "\"The Republican Party is the political party that Donald J. Trump is campaigning to purge of his critics, including Liz Cheney.\"",
                "source_id": "chunk-1ffb4e2302caebd3fef76d6d2ad04cec"
            }
        ],
        "relationships": [
            {
                "src_id": "\"JOE BIDEN\"",
                "tgt_id": "\"INFLATION REDUCTION ACT\"",
                "weight": 10.0,
                "description": "\"Joe Biden signed the Inflation Reduction Act into law, which is a significant part of his economic agenda.\"",
                "source_id": "chunk-1ffb4e2302caebd3fef76d6d2ad04cec"
            },
            {
                "src_id": "\"JOE BIDEN\"",
                "tgt_id": "\"MEDICARE\"",
                "weight": 8.0,
                "description": "\"Joe Biden's Inflation Reduction Act includes provisions that will lower prescription drug costs for seniors on Medicare.\"",
                "source_id": "chunk-1ffb4e2302caebd3fef76d6d2ad04cec"
            },
            {
                "src_id": "\"JOE BIDEN\"",
                "tgt_id": "\"AMERICAN ECONOMY\"",
                "weight": 9.0,
                "description": "\"Joe Biden's goal includes modernizing the American economy through the Inflation Reduction Act.\"",
                "source_id": "chunk-1ffb4e2302caebd3fef76d6d2ad04cec"
            },
            {
                "src_id": "\"DONALD J. TRUMP\"",
                "tgt_id": "\"LIZ CHENEY\"",
                "weight": 7.0,
                "description": "\"Donald J. Trump's campaign to purge the Republican Party of his critics led to Liz Cheney's defeat in the Republican primary.\"",
                "source_id": "chunk-1ffb4e2302caebd3fef76d6d2ad04cec"
            },
            {
                "src_id": "\"DONALD J. TRUMP\"",
                "tgt_id": "\"HARRIET HAGEMAN\"",
                "weight": 8.0,
                "description": "\"Harriet Hageman was endorsed by Donald J. Trump and won the Republican primary against Liz Cheney.\"",
                "source_id": "chunk-1ffb4e2302caebd3fef76d6d2ad04cec"
            },
            {
                "src_id": "\"LIZ CHENEY\"",
                "tgt_id": "\"HARRIET HAGEMAN\"",
                "weight": 10.0,
                "description": "\"Harriet Hageman defeated Liz Cheney in the Republican primary, ending Cheney's role in Congress.\"",
                "source_id": "chunk-1ffb4e2302caebd3fef76d6d2ad04cec"
            },
            {
                "src_id": "\"ELECTRIC UTILITIES\"",
                "tgt_id": "\"INFLATION REDUCTION ACT\"",
                "weight": 7.0,
                "description": "\"The Inflation Reduction Act includes provisions to help electric utilities switch to lower-emission sources of energy.\"",
                "source_id": "chunk-1ffb4e2302caebd3fef76d6d2ad04cec"
            },
            {
                "src_id": "\"CONGRESSIONAL DEMOCRATS\"",
                "tgt_id": "\"INFLATION REDUCTION ACT\"",
                "weight": 8.0,
                "description": "\"Congressional Democrats were involved in intense negotiations to pass the Inflation Reduction Act.\"",
                "source_id": "chunk-1ffb4e2302caebd3fef76d6d2ad04cec"
            },
            {
                "src_id": "\"DEMOCRATIC PARTY\"",
                "tgt_id": "\"INFLATION REDUCTION ACT\"",
                "weight": 7.0,
                "description": "\"The Inflation Reduction Act was passed with the support of the Democratic Party, which holds a slim majority in Congress.\"",
                "source_id": "chunk-1ffb4e2302caebd3fef76d6d2ad04cec"
            }
        ]
    }
}