{
    "image_1": [
        {
            "merged_entity_name": "Ukrainian Troops",
            "entity_type": "PERSON",
            "description": "War-weary Ukrainian troops, also referred to as 'SOLDIER 1', 'SOLDIER 2', and 'SOLDIER 3', are on the eastern front line in Vuhledar, Ukraine, where they are outmanned, outgunned, and digging in. They are described as wearing camouflage uniforms, helmets, and backpacks, walking on debris-covered ground.",
            "source_image_entities": [
                "SOLDIER 1",
                "SOLDIER 2",
                "SOLDIER 3"
            ],
            "source_text_entities": [
                "UKRAINIAN FORCES"
            ]
        },
        {
            "merged_entity_name": "Vuhledar",
            "entity_type": "GEO",
            "description": "Vuhledar is a location on the eastern front line in Ukraine where Ukrainian troops are outmanned and outgunned, walking on debris-covered ground, as described in the image entities.",
            "source_image_entities": [
                "DEBRIS-COVERED GROUND"
            ],
            "source_text_entities": [
                "VUHLEDAR"
            ]
        },
        {
            "merged_entity_name": "Damaged Building",
            "entity_type": "GEO",
            "description": "A large multi-story building with extensive damage, missing windows, and exposed interiors, located in the war-torn area of Ukraine.",
            "source_image_entities": [
                "DAMAGED BUILDING"
            ],
            "source_text_entities": []
        }
    ],
    "image_2": [
        {
            "merged_entity_name": "THE MIRAGE",
            "entity_type": "ORGANIZATION",
            "description": "A hotel and casino in Las Vegas, featuring a large billboard with the faces of The Beatles and the word 'LOVE' on it, as well as palm trees in front of the building.",
            "source_image_entities": [
                "THE MIRAGE",
                "PALM TREES"
            ],
            "source_text_entities": []
        },
        {
            "merged_entity_name": "BUS",
            "entity_type": "OBJECT",
            "description": "A public transportation bus with passengers inside, driving past The Mirage.",
            "source_image_entities": [
                "BUS"
            ],
            "source_text_entities": []
        },
        {
            "merged_entity_name": "PASSENGERS",
            "entity_type": "PERSON",
            "description": "People sitting inside the bus, some looking out the windows.",
            "source_image_entities": [
                "PASSENGERS"
            ],
            "source_text_entities": []
        }
    ],
    "image_3": [
        {
            "merged_entity_name": "WATER METERS",
            "entity_type": "UNKNOWN",
            "description": "Water Meters是从image_3中提取的实体，指Siemens承诺在Jackson安装的现代水表，旨在增加收入并修复基础设施。",
            "source_image_entities": [
                "WATER METERS"
            ],
            "source_text_entities": [
                "SIEMENS"
            ]
        },
        {
            "merged_entity_name": "RORY DOYLE",
            "entity_type": "UNKNOWN",
            "description": "Rory Doyle是从image_3中提取的实体，可能与报道Jackson水危机的新闻有关。",
            "source_image_entities": [
                "RORY DOYLE"
            ],
            "source_text_entities": [
                "JACKSON"
            ]
        },
        {
            "merged_entity_name": "THE NEW YORK TIMES",
            "entity_type": "UNKNOWN",
            "description": "The New York Times是从image_3中提取的实体，可能是报道Jackson水危机和Siemens水表项目的文章来源。",
            "source_image_entities": [
                "THE NEW YORK TIMES"
            ],
            "source_text_entities": [
                "JACKSON",
                "SIEMENS"
            ]
        }
    ],
    "image_4": [
        {
            "merged_entity_name": "PRINCE CHARLES",
            "entity_type": "PERSON",
            "description": "An elderly man with white hair, wearing a dark suit and tie, waving his right hand, who is the monarch of Britain and has been diagnosed with cancer.",
            "source_image_entities": [
                "PRINCE CHARLES",
                "SUIT",
                "TIE",
                "WAVE"
            ],
            "source_text_entities": [
                "KING CHARLES III"
            ]
        }
    ],
    "image_5": [
        {
            "merged_entity_name": "MISSISSIPPI",
            "entity_type": "GEO",
            "description": "Mississippi is the state where Jackson is located, experiencing a water crisis during the summer of 2022, with state officials criticized for their role in the crisis.",
            "source_image_entities": [
                "BACKGROUND"
            ],
            "source_text_entities": [
                "MISSISSIPPI",
                "JACKSON"
            ]
        },
        {
            "merged_entity_name": "JACKSON",
            "entity_type": "GEO",
            "description": "Jackson is a city in Mississippi facing a water crisis, with issues of leaky pipes and economic decline, and is the subject of a blame game between local and state leaders.",
            "source_image_entities": [
                "WOMAN"
            ],
            "source_text_entities": [
                "JACKSON",
                "MISSISSIPPI"
            ]
        },
        {
            "merged_entity_name": "SIEMENS",
            "entity_type": "ORGANIZATION",
            "description": "Siemens is a German corporation that promised to install modern water meters in Jackson to boost revenue and fix infrastructure, but their involvement led to further complications.",
            "source_image_entities": [],
            "source_text_entities": [
                "SIEMENS",
                "JACKSON"
            ]
        }
    ],
    "image_6": [
        {
            "merged_entity_name": "Siemens",
            "entity_type": "ORGANIZATION",
            "description": "Siemens is a German corporation that promised to install modern water meters in Jackson to boost revenue and fix infrastructure, as seen in the image where a person is administering liquid to a parrot, symbolizing the attempt to fix issues.",
            "source_image_entities": [
                "SYRINGE"
            ],
            "source_text_entities": [
                "SIEMENS"
            ]
        }
    ]
}